pakit/main.py
pakit/task.py
pakit/recipe.py
pakit/shell.py
pakit/__init__.py
pakit/exc.py
pakit/graph.py
pakit/conf.py
pakit/extra/README.md
pakit/extra/DEMO.md
pakit/extra/pakit.1
pakit/extra/CHANGELOG
pakit/extra/LICENSE
pakit/extra/completion/README.md
pakit/extra/completion/pakit-bash.sh
pakit-0.2.5.dist-info/entry_points.txt
pakit-0.2.5.dist-info/DESCRIPTION.rst
pakit-0.2.5.dist-info/WHEEL
pakit-0.2.5.dist-info/metadata.json
pakit-0.2.5.dist-info/top_level.txt
pakit-0.2.5.dist-info/RECORD
pakit-0.2.5.dist-info/METADATA
