Metadata-Version: 2.0
Name: pakit
Version: 0.2.5
Summary: A python based package manager that builds programs from source
Home-page: https://github.com/starcraftman/pakit
Author: Jeremy Pallats / starcraft.man
Author-email: N/A
License: BSD
Keywords: development
Platform: any
Classifier: Development Status :: 2 - Pre-Alpha
Classifier: Environment :: Console
Classifier: Intended Audience :: Developers
Classifier: Intended Audience :: End Users/Desktop
Classifier: License :: OSI Approved :: BSD License
Classifier: Operating System :: POSIX :: Linux
Classifier: Programming Language :: Python
Classifier: Programming Language :: Python :: 2
Classifier: Programming Language :: Python :: 2.7
Classifier: Programming Language :: Python :: 3
Classifier: Programming Language :: Python :: 3.2
Classifier: Programming Language :: Python :: 3.3
Classifier: Programming Language :: Python :: 3.4
Classifier: Programming Language :: Python :: 3.5
Classifier: Topic :: Software Development :: Build Tools
Classifier: Topic :: System :: Installation/Setup
Requires-Dist: argparse
Requires-Dist: pyyaml
Provides-Extra: dev
Requires-Dist: pyandoc; extra == 'dev'
Provides-Extra: test
Requires-Dist: coverage; extra == 'test'
Requires-Dist: flake8; extra == 'test'
Requires-Dist: mock; extra == 'test'
Requires-Dist: pytest; extra == 'test'
Requires-Dist: sphinx; extra == 'test'
Requires-Dist: tox; extra == 'test'
